vox_logstash/__init__.py
vox_logstash/log_formatters.py
vox_logstash/log_handlers.py
vox_logstash/tests.py
vox_logstash-0.1.1.dist-info/WHEEL
vox_logstash-0.1.1.dist-info/METADATA
vox_logstash-0.1.1.dist-info/RECORD
