Metadata-Version: 2.1
Name: vox-logstash
Version: 0.1.1
Summary: python logs integration with logstash
License: MIT
Author: Jhonatan Teixeira
Author-email: jhonatan.teixeira@gmail.com
Requires-Python: >=3.8,<4.0
Classifier: License :: OSI Approved :: MIT License
Classifier: Programming Language :: Python :: 3
Classifier: Programming Language :: Python :: 3.8
Classifier: Programming Language :: Python :: 3.9
Requires-Dist: django
